eNlightSDK/__init__.py
eNlightSDK/enlight_cloud.py
eNlightSDK/classes/__init__.py
eNlightSDK/classes/caller.py
eNlightSDK/classes/compute.py
eNlightSDK/classes/default_pod.py
eNlightSDK/classes/diskqos.py
eNlightSDK/classes/flavor.py
eNlightSDK/classes/get_config.py
eNlightSDK/classes/ipam.py
eNlightSDK/classes/network.py
eNlightSDK/classes/queue.py
eNlightSDK/classes/set_projects.py
eNlightSDK/classes/template.py
eNlightSDK/classes/vm.py
eNlightSDKtest-1.0.dist-info/METADATA
eNlightSDKtest-1.0.dist-info/WHEEL
eNlightSDKtest-1.0.dist-info/top_level.txt
eNlightSDKtest-1.0.dist-info/RECORD
